noteparser/__init__.py
noteparser/cli.py
noteparser/core.py
noteparser/exceptions.py
noteparser/converters/__init__.py
noteparser/converters/latex.py
noteparser/db/__init__.py
noteparser/db/migrate.py
noteparser/db/seed.py
noteparser/integration/__init__.py
noteparser/integration/ai_services.py
noteparser/integration/org_sync.py
noteparser/integration/service_client.py
noteparser/parsers/__init__.py
noteparser/parsers/audio.py
noteparser/parsers/ocr.py
noteparser/plugins/__init__.py
noteparser/plugins/base.py
noteparser/plugins/registry.py
noteparser/plugins/builtin/__init__.py
noteparser/plugins/builtin/cs_plugin.py
noteparser/plugins/builtin/math_plugin.py
noteparser/utils/__init__.py
noteparser/utils/academic.py
noteparser/utils/metadata.py
noteparser/web/__init__.py
noteparser/web/api.py
noteparser/web/app.py
noteparser/web/templates/ai_dashboard.html
noteparser/web/templates/base.html
noteparser/web/templates/dashboard.html
noteparser/web/templates/error.html
noteparser/web/templates/file_info.html
noteparser/web/templates/file_viewer.html
noteparser/web/templates/parse.html
noteparser/web/templates/repository.html
noteparser-2.1.2.dist-info/licenses/LICENSE
noteparser-2.1.2.dist-info/METADATA
noteparser-2.1.2.dist-info/WHEEL
noteparser-2.1.2.dist-info/entry_points.txt
noteparser-2.1.2.dist-info/top_level.txt
noteparser-2.1.2.dist-info/RECORD
