Metadata-Version: 2.4
Name: noteparser
Version: 2.1.2
Summary: A comprehensive document parser with AI-powered intelligence for converting and analyzing academic materials
Author-email: Suryansh Sijwali <suryanshss1011@gmail.com>
License-Expression: MIT
Project-URL: Homepage, https://github.com/CollegeNotesOrg/noteparser
Project-URL: Issues, https://github.com/CollegeNotesOrg/noteparser/issues
Keywords: markdown,latex,document,parser,converter,pdf,docx,pptx,ai,semantic-search,knowledge-graph,rag
Classifier: Development Status :: 4 - Beta
Classifier: Intended Audience :: Developers
Classifier: Programming Language :: Python :: 3
Classifier: Programming Language :: Python :: 3.10
Classifier: Programming Language :: Python :: 3.11
Classifier: Programming Language :: Python :: 3.12
Requires-Python: >=3.10
License-File: LICENSE
Requires-Dist: click>=8.0.0
Requires-Dist: pyyaml>=6.0
Requires-Dist: rich>=13.0
Requires-Dist: markitdown>=0.1.0
Requires-Dist: flask>=2.3.0
Requires-Dist: speechrecognition>=3.10.0
Requires-Dist: moviepy>=1.0.3
Requires-Dist: pydub>=0.25.1
Requires-Dist: pytesseract>=0.3.10
Requires-Dist: pillow>=10.0.0
Requires-Dist: opencv-python>=4.8.0
Requires-Dist: numpy>=1.24.0
Requires-Dist: python-docx>=1.0.0
Requires-Dist: python-pptx>=0.6.0
Requires-Dist: openpyxl>=3.1.0
Requires-Dist: pypdf>=3.17.0
Requires-Dist: pdfplumber>=0.10.0
Requires-Dist: beautifulsoup4>=4.12.0
Requires-Dist: lxml>=4.9.0
Requires-Dist: requests>=2.31.0
Requires-Dist: gunicorn>=21.2.0
Requires-Dist: python-dotenv>=1.0.0
Requires-Dist: aiohttp>=3.9.0
Provides-Extra: ai
Requires-Dist: httpx>=0.25.0; extra == "ai"
Requires-Dist: sentence-transformers>=2.2.0; extra == "ai"
Requires-Dist: faiss-cpu>=1.7.4; extra == "ai"
Requires-Dist: tiktoken>=0.5.0; extra == "ai"
Requires-Dist: langchain>=0.1.0; extra == "ai"
Requires-Dist: openai>=1.0.0; extra == "ai"
Requires-Dist: tenacity>=8.2.0; extra == "ai"
Requires-Dist: sqlalchemy>=2.0.0; extra == "ai"
Requires-Dist: alembic>=1.12.0; extra == "ai"
Requires-Dist: redis>=5.0.0; extra == "ai"
Requires-Dist: psycopg2-binary>=2.9.0; extra == "ai"
Requires-Dist: elasticsearch>=8.11.0; extra == "ai"
Requires-Dist: prometheus-client>=0.19.0; extra == "ai"
Requires-Dist: opentelemetry-api>=1.20.0; extra == "ai"
Requires-Dist: opentelemetry-sdk>=1.20.0; extra == "ai"
Requires-Dist: opentelemetry-instrumentation-flask>=0.42b0; extra == "ai"
Requires-Dist: structlog>=23.2.0; extra == "ai"
Requires-Dist: pydantic>=2.5.0; extra == "ai"
Requires-Dist: marshmallow>=3.20.0; extra == "ai"
Requires-Dist: fastapi>=0.104.0; extra == "ai"
Provides-Extra: dev
Requires-Dist: pytest>=7.0.0; extra == "dev"
Requires-Dist: pytest-cov>=4.0.0; extra == "dev"
Requires-Dist: black>=23.0.0; extra == "dev"
Requires-Dist: ruff>=0.1.0; extra == "dev"
Requires-Dist: mypy>=1.0.0; extra == "dev"
Requires-Dist: pre-commit>=3.0.0; extra == "dev"
Requires-Dist: pytest-mock>=3.10.0; extra == "dev"
Requires-Dist: pytest-asyncio>=0.21.0; extra == "dev"
Requires-Dist: pytest-benchmark>=4.0.0; extra == "dev"
Requires-Dist: pytest-xdist>=3.3.0; extra == "dev"
Requires-Dist: pytest-html>=3.2.0; extra == "dev"
Requires-Dist: tox>=4.0.0; extra == "dev"
Requires-Dist: responses>=0.24.0; extra == "dev"
Requires-Dist: httpx>=0.25.0; extra == "dev"
Requires-Dist: isort>=5.12.0; extra == "dev"
Requires-Dist: pylint>=2.17.0; extra == "dev"
Requires-Dist: sphinx>=7.0.0; extra == "dev"
Requires-Dist: sphinx-rtd-theme>=1.3.0; extra == "dev"
Requires-Dist: sphinx-click>=5.0.0; extra == "dev"
Requires-Dist: myst-parser>=2.0.0; extra == "dev"
Requires-Dist: mkdocs>=1.5.0; extra == "dev"
Requires-Dist: mkdocs-material>=9.4.0; extra == "dev"
Requires-Dist: mkdocs-git-revision-date-localized-plugin>=1.2.0; extra == "dev"
Requires-Dist: mkdocs-minify-plugin>=0.7.0; extra == "dev"
Requires-Dist: ipython>=8.12.0; extra == "dev"
Requires-Dist: ipdb>=0.13.0; extra == "dev"
Requires-Dist: jupyter>=1.0.0; extra == "dev"
Requires-Dist: notebook>=7.0.0; extra == "dev"
Requires-Dist: memory-profiler>=0.61.0; extra == "dev"
Requires-Dist: line-profiler>=4.0.0; extra == "dev"
Requires-Dist: psutil>=5.9.0; extra == "dev"
Requires-Dist: bandit>=1.7.0; extra == "dev"
Requires-Dist: safety>=2.3.0; extra == "dev"
Requires-Dist: types-PyYAML>=6.0.0; extra == "dev"
Provides-Extra: all
Requires-Dist: pymupdf>=1.23.0; extra == "all"
Requires-Dist: httpx>=0.25.0; extra == "all"
Requires-Dist: sentence-transformers>=2.2.0; extra == "all"
Requires-Dist: faiss-cpu>=1.7.4; extra == "all"
Requires-Dist: tiktoken>=0.5.0; extra == "all"
Requires-Dist: langchain>=0.1.0; extra == "all"
Requires-Dist: openai>=1.0.0; extra == "all"
Requires-Dist: tenacity>=8.2.0; extra == "all"
Requires-Dist: sqlalchemy>=2.0.0; extra == "all"
Requires-Dist: alembic>=1.12.0; extra == "all"
Requires-Dist: redis>=5.0.0; extra == "all"
Requires-Dist: psycopg2-binary>=2.9.0; extra == "all"
Requires-Dist: elasticsearch>=8.11.0; extra == "all"
Requires-Dist: prometheus-client>=0.19.0; extra == "all"
Requires-Dist: opentelemetry-api>=1.20.0; extra == "all"
Requires-Dist: opentelemetry-sdk>=1.20.0; extra == "all"
Requires-Dist: opentelemetry-instrumentation-flask>=0.42b0; extra == "all"
Requires-Dist: structlog>=23.2.0; extra == "all"
Requires-Dist: pydantic>=2.5.0; extra == "all"
Requires-Dist: marshmallow>=3.20.0; extra == "all"
Requires-Dist: fastapi>=0.104.0; extra == "all"
Dynamic: license-file
